dalle_pytorch/__init__.py
dalle_pytorch/attention.py
dalle_pytorch/dalle_pytorch.py
dalle_pytorch/distributed_utils.py
dalle_pytorch/loader.py
dalle_pytorch/reversible.py
dalle_pytorch/tokenizer.py
dalle_pytorch/transformer.py
dalle_pytorch/vae.py
dalle_pytorch/version.py
dalle_pytorch/data/bpe_simple_vocab_16e6.txt
dalle_pytorch/distributed_backends/__init__.py
dalle_pytorch/distributed_backends/deepspeed_backend.py
dalle_pytorch/distributed_backends/distributed_backend.py
dalle_pytorch/distributed_backends/dummy_backend.py
dalle_pytorch/distributed_backends/horovod_backend.py
dalle_pytorch-1.6.6.dist-info/LICENSE
dalle_pytorch-1.6.6.dist-info/METADATA
dalle_pytorch-1.6.6.dist-info/WHEEL
dalle_pytorch-1.6.6.dist-info/top_level.txt
dalle_pytorch-1.6.6.dist-info/RECORD
