Metadata-Version: 2.1
Name: dalle-pytorch
Version: 1.6.6
Summary: DALL-E - Pytorch
Home-page: https://github.com/lucidrains/dalle-pytorch
Author: Phil Wang
Author-email: lucidrains@gmail.com
License: MIT
Keywords: artificial intelligence,attention mechanism,transformers,text-to-image
Classifier: Development Status :: 4 - Beta
Classifier: Intended Audience :: Developers
Classifier: Topic :: Scientific/Engineering :: Artificial Intelligence
Classifier: License :: OSI Approved :: MIT License
Classifier: Programming Language :: Python :: 3.6
License-File: LICENSE
Requires-Dist: axial-positional-embedding
Requires-Dist: DALL-E
Requires-Dist: einops (>=0.3.2)
Requires-Dist: ftfy
Requires-Dist: packaging
Requires-Dist: pillow
Requires-Dist: regex
Requires-Dist: rotary-embedding-torch
Requires-Dist: taming-transformers-rom1504
Requires-Dist: tokenizers
Requires-Dist: torch (>=1.6)
Requires-Dist: torchvision
Requires-Dist: transformers
Requires-Dist: tqdm
Requires-Dist: youtokentome
Requires-Dist: WebDataset
